Metadata-Version: 2.1
Name: wayscript-legacy
Version: 0.1.3
Summary: WayScript gives you flexible building blocks to seamlessly integrate, automate and host tools in the cloud.
Home-page: https://github.com/wayscript/wayscript-python-legacy
Author: Team WayScript
Author-email: founders@wayscript.com
License: MIT
Keywords: wayscript,productivity,software,superpowers,scripts,cloud,tools,backend,visual,low-code,modules,trigger,integration,dev,http,webhook
Platform: UNKNOWN
Classifier: Development Status :: 4 - Beta
Classifier: Intended Audience :: Developers
Classifier: Intended Audience :: End Users/Desktop
Classifier: Intended Audience :: Science/Research
Classifier: Topic :: Software Development :: Libraries :: Python Modules
Classifier: Topic :: Communications
Classifier: Topic :: Database
Classifier: Topic :: Office/Business
Classifier: Topic :: Utilities
Classifier: Programming Language :: Python :: 3
Classifier: Programming Language :: Python :: 3.6
Classifier: Programming Language :: Python :: 3.7
Classifier: Programming Language :: Python :: Implementation :: CPython
Classifier: License :: OSI Approved :: MIT License
Classifier: Operating System :: OS Independent
Classifier: Natural Language :: English
License-File: LICENSE.txt
